[
    {
        "en_raw": "Hello!",
        "en_clean": "Hello!",
        "jp_raw": "こんにちは！",
        "jp_clean": "こんにちは！",
        "checked": false
    },
    {
        "en_raw": "Ah... Aren't you one of the saviors traveling with Mirabelle?",
        "en_clean": "Ah... Aren't you one of the saviors traveling with Mirabelle?",
        "jp_raw": "あれ... きみはミラベルと旅する救国の英雄一行の？",
        "jp_clean": "あれ... きみはミラベルと旅する救国の英雄一行の？",
        "checked": false
    },
    {
        "en_raw": "You're doing so much for us. I wish I could help you in some way.",
        "en_clean": "You're doing so much for us. I wish I could help you in some way.",
        "jp_raw": "きみたちのしていることはすばらしいことだ。私も役に立てればよいのだが。",
        "jp_clean": "きみたちのしていることはすばらしいことだ。私も役に立てればよいのだが。",
        "checked": false
    },
    {
        "en_raw": "...I know!",
        "en_clean": "...I know!",
        "jp_raw": "...そうだ！",
        "jp_clean": "...そうだ！",
        "checked": false
    },
    {
        "en_raw": "I grow flowers... Beautiful flowers that could make someone you like happy!",
        "en_clean": "I grow flowers... Beautiful flowers that could make someone you like happy!",
        "jp_raw": "私が育てている花... 美しい花は、君の好きな人を幸せな気分にしてくれる！",
        "jp_clean": "私が育てている花... 美しい花は、君の好きな人を幸せな気分にしてくれる！",
        "checked": false
    },
    {
        "en_raw": "Here, have one! You could keep it, or gift it to someone special.",
        "en_clean": "Here, have one! You could keep it, or gift it to someone special.",
        "jp_raw": "さあ、1輪あげるよ！ 自分で持っていてもいいし、特別な人に渡してもいい。",
        "jp_clean": "さあ、1輪あげるよ！ 自分で持っていてもいいし、特別な人に渡してもいい。",
        "checked": false
    },
    {
        "en_raw": "(You got the BRIGHT FLOWER!)",
        "en_clean": "(You got the BRIGHT FLOWER!)",
        "jp_raw": "(「派手な花」を手に入れた！)",
        "jp_clean": "(「派手な花」を手に入れた！)",
        "checked": false
    },
    {
        "en_raw": "(You put the flower in your pocket along with your Souvenirs.)",
        "en_clean": "(You put the flower in your pocket along with your Souvenirs.)",
        "jp_raw": "(ポケットの「思い出の品」に入れておこう。)",
        "jp_clean": "(ポケットの「思い出の品」に入れておこう。)",
        "checked": false
    },
    {
        "en_raw": "[You can give the Flower to one of your party members by talking to them!]",
        "en_clean": "[You can give the Flower to one of your party members by talking to them!]",
        "jp_raw": "[この花はパーティーの誰かに話しかけて渡すことができるよ！]",
        "jp_clean": "[この花はパーティーの誰かに話しかけて渡すことができるよ！]",
        "checked": false
    },
    {
        "en_raw": "(You got the flower again!)",
        "en_clean": "(You got the flower again!)",
        "jp_raw": "(もう一度、花を手に入れた！)",
        "jp_clean": "(もう一度、花を手に入れた！)",
        "checked": false
    },
    {
        "en_raw": "(You could give it to someone else this time...)",
        "en_clean": "(You could give it to someone else this time...)",
        "jp_raw": "(今回は誰かに渡してもいい...)",
        "jp_clean": "(今回は誰かに渡してもいい...)",
        "checked": false
    },
    {
        "en_raw": "(...)",
        "en_clean": "(...)",
        "jp_raw": [
            "(...)",
            "(\\..\\..\\..)",
            "(...)\\!\\m[wait]\\^",
            "\\m[clear](...)\\!\\",
            "\\m[clear](...)",
            "(\\|.\\|.\\|.)",
            "\\m[clear]\\shake(...)",
            "\\m[clear](\\..\\..\\..)",
            "(\\..\\..\\..\\.)\\!\\m[wait]\\^",
            "\\m[vs](...)\\!\\m[wait]\\^",
            "\\m[vs](...)\\!\\",
            "(...)\\!\\m[wait]\\m[wait]\\^",
            "\\m[clear](\\..\\..\\..)\\!\\m[wait]\\^",
            "\\m[choicespace](...)\\!\\",
            "\\shake(...)",
            "\\m[vs](\\..\\..\\..)\\!\\",
            "(...)\\!\\",
            "(\\..\\..\\..\\.)",
            "\\m[clear](...)\\!\\m[wait]\\^",
            "(\\..\\..\\..)\\!\\m[wait]\\^",
            "\\m[vs](...)\\m[wait]\\^",
            "(...)\\!\\m[wait]\\m[wait]\\m[wait]\\^",
            "\\m[clear](\\..\\..\\..\\.)",
            "\\m[clear]\\shake(...)\\!\\m[wait]\\^",
            "\\m[clear]\\shake(\\..\\..\\..\\.)",
            "\\m[clear](\\..\\..\\..)\\!\\",
            "\\m[choicespace](\\..\\..\\..)\\!\\",
            "\\m[vs](\\|.\\|.\\|.)\\!\\",
            "(\\..\\..\\..)\\!\\m[wait]",
            "\\m[clear]\\shake(\\..\\..\\..)",
            "\\m[clear](\\|.\\|.\\|.)",
            "(\\..\\..\\..\\.)\\m[wait]",
            "(\\m[wait].\\m[wait].\\m[wait].\\.)",
            "(\\|.\\|.\\|.\\|)\\!\\m[wait]\\^",
            "\\m[vsc](...)\\!\\",
            "(\\m[dot])\\!\\",
            "\\m[vs]\\shake(...)\\!\\",
            "\\m[clear](.\\|.\\|.\\|)",
            "\\m[clear]\\m[rb](...)",
            "\\m[rb]\\m[vs](...)\\!\\",
            "\\m[choicespace]\\m[rb](...)\\!\\",
            "\\m[clear](\\|.\\|.\\|.)\\m[wait]",
            "\\shake(...)\\!\\m[wait]\\^",
            "(\\|.\\|.\\|.)\\!\\m[wait]\\^",
            "(...)\\!\\m[wait]",
            "(\\..\\..\\..)\\m[wait]\\^",
            "\\m[clear](\\..\\..\\..)\\m[wait]\\^",
            "\\|(\\|.\\|.\\|.\\|)\\m[wait]",
            "\\m[vs]\\m[rb](...)\\!\\",
            "\\m[rb]\\m[clear](...)",
            "\\m[rb]\\m[clear](\\..\\..\\..)",
            "\\m[clear](\\|.\\|.\\|.\\|)\\!\\m[wait]\\^",
            "\\m[clear](\\..\\..\\..)\\!\\m[wait]",
            "(...)"
        ],
        "jp_clean": [
            "(...)",
            "(...)",
            "(...)",
            "(...)",
            "(...)",
            "(...)",
            "(...)",
            "(...)",
            "(...)",
            "(...)",
            "(...)",
            "(...)",
            "(...)",
            "(...)",
            "(...)",
            "(...)",
            "(...)",
            "(...)",
            "(...)",
            "(...)",
            "(...)",
            "(...)",
            "(...)",
            "(...)",
            "(...)",
            "(...)",
            "(...)",
            "(...)",
            "(...)",
            "(...)",
            "(...)",
            "(...)",
            "(...)",
            "(...)",
            "(...)",
            "(...)",
            "(...)",
            "(...)",
            "(...)",
            "(...)",
            "(...)",
            "(...)",
            "(...)",
            "(...)",
            "(...)",
            "(...)",
            "(...)",
            "(...)",
            "(...)",
            "(...)",
            "(...)",
            "(...)",
            "(...)",
            "(...)"
        ],
        "checked": false
    },
    {
        "en_raw": "Heh, have you looked around my house? I cannot get rid of those fast enough!",
        "en_clean": "Heh, have you looked around my house? I cannot get rid of those fast enough!",
        "jp_raw": "はは、私の家の周りを見たかい？ 取っても取っても追いつかないほどあるんだ！",
        "jp_clean": "はは、私の家の周りを見たかい？ 取っても取っても追いつかないほどあるんだ！",
        "checked": false
    },
    {
        "en_raw": "That's why everyone in Dormont has some, too.",
        "en_clean": "That's why everyone in Dormont has some, too.",
        "jp_raw": "だから、ドーモント中の人にあげてるよ。",
        "jp_clean": "だから、ドーモント中の人にあげてるよ。",
        "checked": false
    },
    {
        "en_raw": "And... It's just nice, isn't it? To be able to give physical proof of your love to people?",
        "en_clean": "And... It's just nice, isn't it? To be able to give physical proof of your love to people?",
        "jp_raw": "それに... 花はいいものだろう？ 愛の証をかたちにして渡せるものだと思わないかい？",
        "jp_clean": "それに... 花はいいものだろう？ 愛の証をかたちにして渡せるものだと思わないかい？",
        "checked": false
    },
    {
        "en_raw": "(...)",
        "en_clean": "(...)",
        "jp_raw": [
            "(...)",
            "(\\..\\..\\..)",
            "(...)\\!\\m[wait]\\^",
            "\\m[clear](...)\\!\\",
            "\\m[clear](...)",
            "(\\|.\\|.\\|.)",
            "\\m[clear]\\shake(...)",
            "\\m[clear](\\..\\..\\..)",
            "(\\..\\..\\..\\.)\\!\\m[wait]\\^",
            "\\m[vs](...)\\!\\m[wait]\\^",
            "\\m[vs](...)\\!\\",
            "(...)\\!\\m[wait]\\m[wait]\\^",
            "\\m[clear](\\..\\..\\..)\\!\\m[wait]\\^",
            "\\m[choicespace](...)\\!\\",
            "\\shake(...)",
            "\\m[vs](\\..\\..\\..)\\!\\",
            "(...)\\!\\",
            "(\\..\\..\\..\\.)",
            "\\m[clear](...)\\!\\m[wait]\\^",
            "(\\..\\..\\..)\\!\\m[wait]\\^",
            "\\m[vs](...)\\m[wait]\\^",
            "(...)\\!\\m[wait]\\m[wait]\\m[wait]\\^",
            "\\m[clear](\\..\\..\\..\\.)",
            "\\m[clear]\\shake(...)\\!\\m[wait]\\^",
            "\\m[clear]\\shake(\\..\\..\\..\\.)",
            "\\m[clear](\\..\\..\\..)\\!\\",
            "\\m[choicespace](\\..\\..\\..)\\!\\",
            "\\m[vs](\\|.\\|.\\|.)\\!\\",
            "(\\..\\..\\..)\\!\\m[wait]",
            "\\m[clear]\\shake(\\..\\..\\..)",
            "\\m[clear](\\|.\\|.\\|.)",
            "(\\..\\..\\..\\.)\\m[wait]",
            "(\\m[wait].\\m[wait].\\m[wait].\\.)",
            "(\\|.\\|.\\|.\\|)\\!\\m[wait]\\^",
            "\\m[vsc](...)\\!\\",
            "(\\m[dot])\\!\\",
            "\\m[vs]\\shake(...)\\!\\",
            "\\m[clear](.\\|.\\|.\\|)",
            "\\m[clear]\\m[rb](...)",
            "\\m[rb]\\m[vs](...)\\!\\",
            "\\m[choicespace]\\m[rb](...)\\!\\",
            "\\m[clear](\\|.\\|.\\|.)\\m[wait]",
            "\\shake(...)\\!\\m[wait]\\^",
            "(\\|.\\|.\\|.)\\!\\m[wait]\\^",
            "(...)\\!\\m[wait]",
            "(\\..\\..\\..)\\m[wait]\\^",
            "\\m[clear](\\..\\..\\..)\\m[wait]\\^",
            "\\|(\\|.\\|.\\|.\\|)\\m[wait]",
            "\\m[vs]\\m[rb](...)\\!\\",
            "\\m[rb]\\m[clear](...)",
            "\\m[rb]\\m[clear](\\..\\..\\..)",
            "\\m[clear](\\|.\\|.\\|.\\|)\\!\\m[wait]\\^",
            "\\m[clear](\\..\\..\\..)\\!\\m[wait]",
            "(...)"
        ],
        "jp_clean": [
            "(...)",
            "(...)",
            "(...)",
            "(...)",
            "(...)",
            "(...)",
            "(...)",
            "(...)",
            "(...)",
            "(...)",
            "(...)",
            "(...)",
            "(...)",
            "(...)",
            "(...)",
            "(...)",
            "(...)",
            "(...)",
            "(...)",
            "(...)",
            "(...)",
            "(...)",
            "(...)",
            "(...)",
            "(...)",
            "(...)",
            "(...)",
            "(...)",
            "(...)",
            "(...)",
            "(...)",
            "(...)",
            "(...)",
            "(...)",
            "(...)",
            "(...)",
            "(...)",
            "(...)",
            "(...)",
            "(...)",
            "(...)",
            "(...)",
            "(...)",
            "(...)",
            "(...)",
            "(...)",
            "(...)",
            "(...)",
            "(...)",
            "(...)",
            "(...)",
            "(...)",
            "(...)",
            "(...)"
        ],
        "checked": false
    },
    {
        "en_raw": "(It is.)",
        "en_clean": "(It is.)",
        "jp_raw": "(確かに。)",
        "jp_clean": "(確かに。)",
        "checked": false
    },
    {
        "en_raw": "(Not really.)",
        "en_clean": "(Not really.)",
        "jp_raw": "(そうでもないぞ。)",
        "jp_clean": "(そうでもないぞ。)",
        "checked": false
    },
    {
        "en_raw": "(You're learning that physical things fade, too.)",
        "en_clean": "(You're learning that physical things fade, too.)",
        "jp_raw": "(かたちあるものだって衰え、朽ちていく。)",
        "jp_clean": "(かたちあるものだって衰え、朽ちていく。)",
        "checked": false
    },
    {
        "en_raw": "(You need to ask...)",
        "en_clean": "(You need to ask...)",
        "jp_raw": "(聞きたいことは...)",
        "jp_clean": "(聞きたいことは...)",
        "checked": false
    },
    {
        "en_raw": "What I asked the Tree?",
        "en_clean": "What I asked the Tree?",
        "jp_raw": "願いの木に頼んだこと？",
        "jp_clean": "願いの木に頼んだこと？",
        "checked": false
    },
    {
        "en_raw": "...It's private, isn't it?",
        "en_clean": "...It's private, isn't it?",
        "jp_raw": "...それは個人的なことだろう？",
        "jp_clean": "...それは個人的なことだろう？",
        "checked": false
    },
    {
        "en_raw": "I didn't tell the Head Housemaiden, so I don't see why I'd have to tell you. Sorry.",
        "en_clean": "I didn't tell the Head Housemaiden, so I don't see why I'd have to tell you. Sorry.",
        "jp_raw": "侍祭長にだって言わなかったんだ。きみに言う必要はないと思うが。悪いね。",
        "jp_clean": "侍祭長にだって言わなかったんだ。きみに言う必要はないと思うが。悪いね。",
        "checked": false
    },
    {
        "en_raw": "Good luck tomorrow! We're all counting on you!",
        "en_clean": "Good luck tomorrow! We're all counting on you!",
        "jp_raw": "明日はがんばってくれ！ きみたちが頼りだよ！",
        "jp_clean": "明日はがんばってくれ！ きみたちが頼りだよ！",
        "checked": false
    },
    {
        "en_raw": "Hello!",
        "en_clean": "Hello!",
        "jp_raw": "こんにちは！",
        "jp_clean": "こんにちは！",
        "checked": false
    },
    {
        "en_raw": "Ah... Aren't you one of the saviors traveling with Mirabelle?",
        "en_clean": "Ah... Aren't you one of the saviors traveling with Mirabelle?",
        "jp_raw": "あれ... きみはミラベルと旅する救国の英雄一行の？",
        "jp_clean": "あれ... きみはミラベルと旅する救国の英雄一行の？",
        "checked": false
    },
    {
        "en_raw": "You're doing so much for us. I wish I could help you in some way.",
        "en_clean": "You're doing so much for us. I wish I could help you in some way.",
        "jp_raw": "きみたちのしていることはすばらしいことだ。私も役に立てればよいのだが。",
        "jp_clean": "きみたちのしていることはすばらしいことだ。私も役に立てればよいのだが。",
        "checked": false
    },
    {
        "en_raw": "...I know!",
        "en_clean": "...I know!",
        "jp_raw": "...そうだ！",
        "jp_clean": "...そうだ！",
        "checked": false
    },
    {
        "en_raw": "I grow flowers... Beautiful flowers that could make someone you like happy!",
        "en_clean": "I grow flowers... Beautiful flowers that could make someone you like happy!",
        "jp_raw": "私が育てている花... 美しい花は、君の好きな人を幸せな気分にしてくれる！",
        "jp_clean": "私が育てている花... 美しい花は、君の好きな人を幸せな気分にしてくれる！",
        "checked": false
    },
    {
        "en_raw": "Here, have one! You could keep it, or gift it to someone special.",
        "en_clean": "Here, have one! You could keep it, or gift it to someone special.",
        "jp_raw": "さあ、1輪あげるよ！ 自分で持っていてもいいし、特別な人に渡してもいい。",
        "jp_clean": "さあ、1輪あげるよ！ 自分で持っていてもいいし、特別な人に渡してもいい。",
        "checked": false
    },
    {
        "en_raw": "(You got the BRIGHT FLOWER!)",
        "en_clean": "(You got the BRIGHT FLOWER!)",
        "jp_raw": "(「派手な花」を手に入れた！)",
        "jp_clean": "(「派手な花」を手に入れた！)",
        "checked": false
    },
    {
        "en_raw": "(You put the flower in your pocket along with your Souvenirs.)",
        "en_clean": "(You put the flower in your pocket along with your Souvenirs.)",
        "jp_raw": "(ポケットの「思い出の品」に入れておこう。)",
        "jp_clean": "(ポケットの「思い出の品」に入れておこう。)",
        "checked": false
    },
    {
        "en_raw": "(...)",
        "en_clean": "(...)",
        "jp_raw": [
            "(...)",
            "(\\..\\..\\..)",
            "(...)\\!\\m[wait]\\^",
            "\\m[clear](...)\\!\\",
            "\\m[clear](...)",
            "(\\|.\\|.\\|.)",
            "\\m[clear]\\shake(...)",
            "\\m[clear](\\..\\..\\..)",
            "(\\..\\..\\..\\.)\\!\\m[wait]\\^",
            "\\m[vs](...)\\!\\m[wait]\\^",
            "\\m[vs](...)\\!\\",
            "(...)\\!\\m[wait]\\m[wait]\\^",
            "\\m[clear](\\..\\..\\..)\\!\\m[wait]\\^",
            "\\m[choicespace](...)\\!\\",
            "\\shake(...)",
            "\\m[vs](\\..\\..\\..)\\!\\",
            "(...)\\!\\",
            "(\\..\\..\\..\\.)",
            "\\m[clear](...)\\!\\m[wait]\\^",
            "(\\..\\..\\..)\\!\\m[wait]\\^",
            "\\m[vs](...)\\m[wait]\\^",
            "(...)\\!\\m[wait]\\m[wait]\\m[wait]\\^",
            "\\m[clear](\\..\\..\\..\\.)",
            "\\m[clear]\\shake(...)\\!\\m[wait]\\^",
            "\\m[clear]\\shake(\\..\\..\\..\\.)",
            "\\m[clear](\\..\\..\\..)\\!\\",
            "\\m[choicespace](\\..\\..\\..)\\!\\",
            "\\m[vs](\\|.\\|.\\|.)\\!\\",
            "(\\..\\..\\..)\\!\\m[wait]",
            "\\m[clear]\\shake(\\..\\..\\..)",
            "\\m[clear](\\|.\\|.\\|.)",
            "(\\..\\..\\..\\.)\\m[wait]",
            "(\\m[wait].\\m[wait].\\m[wait].\\.)",
            "(\\|.\\|.\\|.\\|)\\!\\m[wait]\\^",
            "\\m[vsc](...)\\!\\",
            "(\\m[dot])\\!\\",
            "\\m[vs]\\shake(...)\\!\\",
            "\\m[clear](.\\|.\\|.\\|)",
            "\\m[clear]\\m[rb](...)",
            "\\m[rb]\\m[vs](...)\\!\\",
            "\\m[choicespace]\\m[rb](...)\\!\\",
            "\\m[clear](\\|.\\|.\\|.)\\m[wait]",
            "\\shake(...)\\!\\m[wait]\\^",
            "(\\|.\\|.\\|.)\\!\\m[wait]\\^",
            "(...)\\!\\m[wait]",
            "(\\..\\..\\..)\\m[wait]\\^",
            "\\m[clear](\\..\\..\\..)\\m[wait]\\^",
            "\\|(\\|.\\|.\\|.\\|)\\m[wait]",
            "\\m[vs]\\m[rb](...)\\!\\",
            "\\m[rb]\\m[clear](...)",
            "\\m[rb]\\m[clear](\\..\\..\\..)",
            "\\m[clear](\\|.\\|.\\|.\\|)\\!\\m[wait]\\^",
            "\\m[clear](\\..\\..\\..)\\!\\m[wait]",
            "(...)"
        ],
        "jp_clean": [
            "(...)",
            "(...)",
            "(...)",
            "(...)",
            "(...)",
            "(...)",
            "(...)",
            "(...)",
            "(...)",
            "(...)",
            "(...)",
            "(...)",
            "(...)",
            "(...)",
            "(...)",
            "(...)",
            "(...)",
            "(...)",
            "(...)",
            "(...)",
            "(...)",
            "(...)",
            "(...)",
            "(...)",
            "(...)",
            "(...)",
            "(...)",
            "(...)",
            "(...)",
            "(...)",
            "(...)",
            "(...)",
            "(...)",
            "(...)",
            "(...)",
            "(...)",
            "(...)",
            "(...)",
            "(...)",
            "(...)",
            "(...)",
            "(...)",
            "(...)",
            "(...)",
            "(...)",
            "(...)",
            "(...)",
            "(...)",
            "(...)",
            "(...)",
            "(...)",
            "(...)",
            "(...)",
            "(...)"
        ],
        "checked": false
    },
    {
        "en_raw": "(But there's no one left to give it to.)",
        "en_clean": "(But there's no one left to give it to.)",
        "jp_raw": "(でも、もう全員に渡した。)",
        "jp_clean": "(でも、もう全員に渡した。)",
        "checked": false
    },
    {
        "en_raw": "(It's a barrel.)",
        "en_clean": "(It's a barrel.)",
        "jp_raw": "(タルだな。)",
        "jp_clean": "(タルだな。)",
        "checked": false
    },
    {
        "en_raw": "(It's full of soil for gardening.)",
        "en_clean": "(It's full of soil for gardening.)",
        "jp_raw": "(園芸用の土でいっぱいだ。)",
        "jp_clean": "(園芸用の土でいっぱいだ。)",
        "checked": false
    },
    {
        "en_raw": "(The closet is full of gardening supplies.)",
        "en_clean": "(The closet is full of gardening supplies.)",
        "jp_raw": "(クローゼットは園芸用品でいっぱいだ。)",
        "jp_clean": "(クローゼットは園芸用品でいっぱいだ。)",
        "checked": false
    },
    {
        "en_raw": "(Flowers.)",
        "en_clean": "(Flowers.)",
        "jp_raw": "(花だ。)",
        "jp_clean": "(花だ。)",
        "checked": false
    },
    {
        "en_raw": "(Wait. Those are fake.)",
        "en_clean": "(Wait. Those are fake.)",
        "jp_raw": "(待てよ。m[wait]これみんな造花だ。)",
        "jp_clean": "(待てよ。これみんな造花だ。)",
        "checked": false
    }
]